pyrio-1.5.0.dist-info/METADATA
pyrio-1.5.0.dist-info/WHEEL
pyrio-1.5.0.dist-info/entry_points.txt
pyrio-1.5.0.dist-info/licenses/LICENSE
pyrio/__init__.py
pyrio/decorators/__init__.py
pyrio/decorators/handler.py
pyrio/decorators/mapper.py
pyrio/exceptions/__init__.py
pyrio/exceptions/exception.py
pyrio/iterators/__init__.py
pyrio/iterators/itertools_mixin.py
pyrio/iterators/stream_generator.py
pyrio/streams/__init__.py
pyrio/streams/base_stream.py
pyrio/streams/file_stream.py
pyrio/streams/stream.py
pyrio/utils/__init__.py
pyrio/utils/dict_item.py
pyrio/utils/optional.py
pyrio-1.5.0.dist-info/RECORD
