Metadata-Version: 2.4
Name: pyrio
Version: 1.5.0
Summary: Functional-style Streams library for processing collections. Supports querying files (json, toml, yaml, xml, csv, tsv, plain text) - as well as creating and updating them. Provides easy integration with itertools
Keywords: stream,functional,processing,collections,fluent API,file processing,queries
Author-Email: kaliv0 <kaloyan.ivanov88@gmail.com>
License-File: LICENSE
Project-URL: Repository, https://github.com/kaliv0/pyrio
Project-URL: Documentation, https://pyrio.readthedocs.io/en/latest
Requires-Python: >=3.12
Provides-Extra: fs
Requires-Dist: pyyaml>=6.0.2; extra == "fs"
Requires-Dist: tomli-w>=1.1.0; extra == "fs"
Requires-Dist: xmltodict>=0.14.2; extra == "fs"
